feid/__init__.py
feid/agent/__init__.py
feid/agent/maestro.py
feid_mas-0.1.0.dist-info/licenses/LICENSE
feid_mas-0.1.0.dist-info/METADATA
feid_mas-0.1.0.dist-info/WHEEL
feid_mas-0.1.0.dist-info/top_level.txt
feid_mas-0.1.0.dist-info/RECORD
