Metadata-Version: 2.4
Name: feid-mas
Version: 0.1.0
Summary: Framework Experimental para Integracion de Datos (FEID) - Multi-Agent Systems
Author-email: Leon Alberne Torres Restrepo <albernetorres@gmail.com>
License-Expression: MIT
Project-URL: Homepage, https://github.com/albernetr
Project-URL: Repository, https://github.com/albernetr/feid
Keywords: multi-agent,agents,mas,fipa,kqml,feid
Requires-Python: >=3.10
License-File: LICENSE
Dynamic: license-file
